{
    "python": {
        "local": {
            "close": [
                0.0,
                0,
                0
            ],
            "constructor": [
                0.0,
                0,
                0
            ],
            "destructor": [
                0.0,
                0,
                0
            ],
            "dummy": [
                0.0,
                0,
                0
            ],
            "fclose": [
                0.0,
                0,
                0
            ],
            "feof": [
                0.0,
                0,
                0
            ],
            "fgetc": [
                0.0,
                0,
                0
            ],
            "fgets": [
                0.0,
                0,
                0
            ],
            "fputc": [
                0.0,
                0,
                0
            ],
            "fputs": [
                0.0,
                0,
                0
            ],
            "fread": [
                0.0,
                0,
                0
            ],
            "fseek": [
                0.0,
                0,
                0
            ],
            "fsync": [
                0.0,
                0,
                0
            ],
            "ftell": [
                0.0,
                0,
                0
            ],
            "fwrite": [
                0.0,
                0,
                0
            ],
            "in_fopen": [
                0.0,
                0,
                0
            ],
            "in_open": [
                0.0,
                0,
                0
            ],
            "out_fopen": [
                0.0,
                0,
                0
            ],
            "out_open": [
                0.0,
                0,
                0
            ],
            "read": [
                0.0,
                0,
                0
            ],
            "readv": [
                0.0,
                0,
                0
            ],
            "rewind": [
                0.0,
                0,
                0
            ],
            "seek": [
                0.0,
                0,
                0
            ],
            "stat": [
                0.0,
                0,
                0
            ],
            "write": [
                0.0,
                0,
                0
            ],
            "writev": [
                0.0,
                0,
                0
            ]
        },
        "monitor": {
            "close": [
                1.062027753,
                23,
                0
            ],
            "constructor": [
                1.1101e-05,
                1,
                0
            ],
            "destructor": [
                8.2623e-05,
                1,
                0
            ],
            "dummy": [
                0.0,
                0,
                0
            ],
            "fclose": [
                0.0,
                0,
                0
            ],
            "feof": [
                0.0,
                0,
                0
            ],
            "fgetc": [
                0.0,
                0,
                0
            ],
            "fgets": [
                0.0,
                0,
                0
            ],
            "fputc": [
                0.0,
                0,
                0
            ],
            "fputs": [
                0.0,
                0,
                0
            ],
            "fread": [
                0.0,
                0,
                0
            ],
            "fseek": [
                0.0,
                0,
                0
            ],
            "fsync": [
                0.0,
                0,
                0
            ],
            "ftell": [
                0.0,
                0,
                0
            ],
            "fwrite": [
                0.0,
                0,
                0
            ],
            "in_fopen": [
                1.058e-05,
                1,
                0
            ],
            "in_open": [
                0.030379583,
                11,
                0
            ],
            "out_fopen": [
                0.0,
                0,
                0
            ],
            "out_open": [
                0.152051201,
                12,
                0
            ],
            "read": [
                0.000897081,
                223,
                4618381
            ],
            "readv": [
                0.0,
                0,
                0
            ],
            "rewind": [
                0.0,
                0,
                0
            ],
            "seek": [
                0.000128136,
                35,
                0
            ],
            "stat": [
                0.04378432,
                11,
                0
            ],
            "write": [
                0.000829641,
                8,
                1953149
            ],
            "writev": [
                0.0,
                0,
                0
            ]
        },
        "system": {
            "close": [
                11.333553333,
                3584,
                0
            ],
            "constructor": [
                0.0,
                0,
                0
            ],
            "destructor": [
                0.0,
                0,
                0
            ],
            "dummy": [
                0.0,
                0,
                0
            ],
            "fclose": [
                0.0,
                0,
                0
            ],
            "feof": [
                0.0,
                0,
                0
            ],
            "fgetc": [
                0.0,
                0,
                0
            ],
            "fgets": [
                0.0,
                0,
                0
            ],
            "fputc": [
                0.0,
                0,
                0
            ],
            "fputs": [
                0.0,
                0,
                0
            ],
            "fread": [
                0.0,
                0,
                0
            ],
            "fseek": [
                0.0,
                0,
                0
            ],
            "fsync": [
                0.0,
                0,
                0
            ],
            "ftell": [
                3.1e-06,
                1,
                0
            ],
            "fwrite": [
                0.0,
                0,
                0
            ],
            "in_fopen": [
                0.001514191,
                73,
                0
            ],
            "in_open": [
                2.213866367,
                970,
                0
            ],
            "out_fopen": [
                0.926619648,
                18,
                0
            ],
            "out_open": [
                32.705133811,
                2509,
                0
            ],
            "read": [
                0.023714146,
                1934,
                12479668
            ],
            "readv": [
                0.0,
                0,
                0
            ],
            "rewind": [
                0.0,
                0,
                0
            ],
            "seek": [
                0.003120692,
                4414,
                0
            ],
            "stat": [
                4.057248924,
                4540,
                0
            ],
            "write": [
                2.040516638,
                2527,
                11442720
            ],
            "writev": [
                0.0,
                0,
                0
            ]
        }
    }
}