{
    "python": {
        "local": {
            "close": [
                0.0,
                0,
                0
            ],
            "constructor": [
                0.0,
                0,
                0
            ],
            "destructor": [
                0.0,
                0,
                0
            ],
            "dummy": [
                0.0,
                0,
                0
            ],
            "fclose": [
                0.0,
                0,
                0
            ],
            "feof": [
                0.0,
                0,
                0
            ],
            "fgetc": [
                0.0,
                0,
                0
            ],
            "fgets": [
                0.0,
                0,
                0
            ],
            "fputc": [
                0.0,
                0,
                0
            ],
            "fputs": [
                0.0,
                0,
                0
            ],
            "fread": [
                0.0,
                0,
                0
            ],
            "fseek": [
                0.0,
                0,
                0
            ],
            "fsync": [
                0.0,
                0,
                0
            ],
            "ftell": [
                0.0,
                0,
                0
            ],
            "fwrite": [
                0.0,
                0,
                0
            ],
            "in_fopen": [
                0.0,
                0,
                0
            ],
            "in_open": [
                0.0,
                0,
                0
            ],
            "out_fopen": [
                0.0,
                0,
                0
            ],
            "out_open": [
                0.0,
                0,
                0
            ],
            "read": [
                0.0,
                0,
                0
            ],
            "readv": [
                0.0,
                0,
                0
            ],
            "rewind": [
                0.0,
                0,
                0
            ],
            "seek": [
                0.0,
                0,
                0
            ],
            "stat": [
                0.0,
                0,
                0
            ],
            "write": [
                0.0,
                0,
                0
            ],
            "writev": [
                0.0,
                0,
                0
            ]
        },
        "monitor": {
            "close": [
                0.226218524,
                23,
                0
            ],
            "constructor": [
                1.367e-05,
                1,
                0
            ],
            "destructor": [
                5.1249e-05,
                1,
                0
            ],
            "dummy": [
                0.0,
                0,
                0
            ],
            "fclose": [
                0.0,
                0,
                0
            ],
            "feof": [
                0.0,
                0,
                0
            ],
            "fgetc": [
                0.0,
                0,
                0
            ],
            "fgets": [
                0.0,
                0,
                0
            ],
            "fputc": [
                0.0,
                0,
                0
            ],
            "fputs": [
                0.0,
                0,
                0
            ],
            "fread": [
                0.0,
                0,
                0
            ],
            "fseek": [
                0.0,
                0,
                0
            ],
            "fsync": [
                0.0,
                0,
                0
            ],
            "ftell": [
                0.0,
                0,
                0
            ],
            "fwrite": [
                0.0,
                0,
                0
            ],
            "in_fopen": [
                1.353e-05,
                1,
                0
            ],
            "in_open": [
                0.021227945,
                11,
                0
            ],
            "out_fopen": [
                0.0,
                0,
                0
            ],
            "out_open": [
                0.066465823,
                12,
                0
            ],
            "read": [
                0.000759153,
                122,
                3011864
            ],
            "readv": [
                0.0,
                0,
                0
            ],
            "rewind": [
                0.0,
                0,
                0
            ],
            "seek": [
                8.746e-05,
                35,
                0
            ],
            "stat": [
                0.040650867,
                11,
                0
            ],
            "write": [
                0.000515405,
                9,
                1379137
            ],
            "writev": [
                0.0,
                0,
                0
            ]
        },
        "system": {
            "close": [
                11.104593725,
                3603,
                0
            ],
            "constructor": [
                0.0,
                0,
                0
            ],
            "destructor": [
                0.0,
                0,
                0
            ],
            "dummy": [
                0.0,
                0,
                0
            ],
            "fclose": [
                0.0,
                0,
                0
            ],
            "feof": [
                0.0,
                0,
                0
            ],
            "fgetc": [
                0.0,
                0,
                0
            ],
            "fgets": [
                0.0,
                0,
                0
            ],
            "fputc": [
                0.0,
                0,
                0
            ],
            "fputs": [
                0.0,
                0,
                0
            ],
            "fread": [
                0.0,
                0,
                0
            ],
            "fseek": [
                0.0,
                0,
                0
            ],
            "fsync": [
                0.0,
                0,
                0
            ],
            "ftell": [
                2.69e-06,
                1,
                0
            ],
            "fwrite": [
                0.0,
                0,
                0
            ],
            "in_fopen": [
                0.001308768,
                75,
                0
            ],
            "in_open": [
                1.758171337,
                985,
                0
            ],
            "out_fopen": [
                0.165728889,
                20,
                0
            ],
            "out_open": [
                22.363075681,
                2509,
                0
            ],
            "read": [
                0.123472732,
                1963,
                12478783
            ],
            "readv": [
                0.0,
                0,
                0
            ],
            "rewind": [
                0.0,
                0,
                0
            ],
            "seek": [
                0.002631307,
                4443,
                0
            ],
            "stat": [
                3.061396206,
                4541,
                0
            ],
            "write": [
                0.839313118,
                2529,
                10545642
            ],
            "writev": [
                0.0,
                0,
                0
            ]
        }
    }
}