{
    "python3": {
        "local": {
            "close": [
                0.0,
                0,
                0
            ],
            "constructor": [
                0.0,
                0,
                0
            ],
            "destructor": [
                0.0,
                0,
                0
            ],
            "dummy": [
                0.0,
                0,
                0
            ],
            "fclose": [
                0.0,
                0,
                0
            ],
            "feof": [
                0.0,
                0,
                0
            ],
            "fgetc": [
                0.0,
                0,
                0
            ],
            "fgets": [
                0.0,
                0,
                0
            ],
            "fputc": [
                0.0,
                0,
                0
            ],
            "fputs": [
                0.0,
                0,
                0
            ],
            "fread": [
                0.0,
                0,
                0
            ],
            "fseek": [
                0.0,
                0,
                0
            ],
            "fsync": [
                0.0,
                0,
                0
            ],
            "ftell": [
                0.0,
                0,
                0
            ],
            "fwrite": [
                0.0,
                0,
                0
            ],
            "in_fopen": [
                0.0,
                0,
                0
            ],
            "in_open": [
                0.0,
                0,
                0
            ],
            "out_fopen": [
                0.0,
                0,
                0
            ],
            "out_open": [
                0.0,
                0,
                0
            ],
            "read": [
                0.0,
                0,
                0
            ],
            "readv": [
                0.0,
                0,
                0
            ],
            "rewind": [
                0.0,
                0,
                0
            ],
            "seek": [
                0.0,
                0,
                0
            ],
            "stat": [
                0.0,
                0,
                0
            ],
            "write": [
                0.0,
                0,
                0
            ],
            "writev": [
                0.0,
                0,
                0
            ]
        },
        "monitor": {
            "close": [
                1.401810052,
                3,
                0
            ],
            "constructor": [
                1.042e-05,
                1,
                0
            ],
            "destructor": [
                5.561e-05,
                1,
                0
            ],
            "dummy": [
                0.0,
                0,
                0
            ],
            "fclose": [
                0.0,
                0,
                0
            ],
            "feof": [
                0.0,
                0,
                0
            ],
            "fgetc": [
                0.0,
                0,
                0
            ],
            "fgets": [
                0.0,
                0,
                0
            ],
            "fputc": [
                0.0,
                0,
                0
            ],
            "fputs": [
                0.0,
                0,
                0
            ],
            "fread": [
                0.0,
                0,
                0
            ],
            "fseek": [
                0.0,
                0,
                0
            ],
            "fsync": [
                0.0,
                0,
                0
            ],
            "ftell": [
                0.0,
                0,
                0
            ],
            "fwrite": [
                0.0,
                0,
                0
            ],
            "in_fopen": [
                1.116e-05,
                1,
                0
            ],
            "in_open": [
                0.411005603,
                2,
                0
            ],
            "out_fopen": [
                0.0,
                0,
                0
            ],
            "out_open": [
                0.050952008,
                1,
                0
            ],
            "read": [
                19.65053759,
                309988,
                2539397354
            ],
            "readv": [
                0.0,
                0,
                0
            ],
            "rewind": [
                0.0,
                0,
                0
            ],
            "seek": [
                1.148e-05,
                3,
                0
            ],
            "stat": [
                0.0,
                0,
                0
            ],
            "write": [
                4.1059e-05,
                1,
                88261
            ],
            "writev": [
                0.0,
                0,
                0
            ]
        },
        "system": {
            "close": [
                16.117334552,
                10074,
                0
            ],
            "constructor": [
                0.0,
                0,
                0
            ],
            "destructor": [
                0.0,
                0,
                0
            ],
            "dummy": [
                0.0,
                0,
                0
            ],
            "fclose": [
                0.0,
                0,
                0
            ],
            "feof": [
                0.0,
                0,
                0
            ],
            "fgetc": [
                0.0,
                0,
                0
            ],
            "fgets": [
                0.0,
                0,
                0
            ],
            "fputc": [
                0.0,
                0,
                0
            ],
            "fputs": [
                0.0,
                0,
                0
            ],
            "fread": [
                0.0,
                0,
                0
            ],
            "fseek": [
                0.0,
                0,
                0
            ],
            "fsync": [
                0.0,
                0,
                0
            ],
            "ftell": [
                3.08e-06,
                1,
                0
            ],
            "fwrite": [
                0.0,
                0,
                0
            ],
            "in_fopen": [
                0.046286331,
                5013,
                0
            ],
            "in_open": [
                7.051117638,
                2553,
                0
            ],
            "out_fopen": [
                1.391090863,
                3,
                0
            ],
            "out_open": [
                31.41472676,
                2504,
                0
            ],
            "read": [
                0.007124722,
                2191,
                1196773
            ],
            "readv": [
                0.0,
                0,
                0
            ],
            "rewind": [
                0.0,
                0,
                0
            ],
            "seek": [
                0.004095557,
                7615,
                0
            ],
            "stat": [
                7.624362128,
                2756,
                0
            ],
            "write": [
                0.01171378,
                2119,
                741425
            ],
            "writev": [
                0.0,
                0,
                0
            ]
        }
    }
}